dilax/__init__.py
dilax/custom_types.py
dilax/effect.py
dilax/ipy_util.py
dilax/likelihood.py
dilax/model.py
dilax/modifier.py
dilax/optimizer.py
dilax/parameter.py
dilax/pdf.py
dilax/py.typed
dilax/util.py
dilax-0.1.6.dist-info/METADATA
dilax-0.1.6.dist-info/WHEEL
dilax-0.1.6.dist-info/licenses/LICENSE
dilax-0.1.6.dist-info/RECORD
