Metadata-Version: 2.1
Name: dilax
Version: 0.1.6
Summary: Differentiable (binned) likelihoods in JAX.
Project-URL: Homepage, https://github.com/pfackeldey/dilax
Project-URL: Bug Tracker, https://github.com/pfackeldey/dilax/issues
Project-URL: Discussions, https://github.com/pfackeldey/dilax/discussions
Project-URL: Changelog, https://github.com/pfackeldey/dilax/releases
Author-email: Peter Fackeldey <peter.fackeldey@rwth-aachen.de>
License-File: LICENSE
Classifier: Development Status :: 1 - Planning
Classifier: Intended Audience :: Developers
Classifier: Intended Audience :: Science/Research
Classifier: License :: OSI Approved :: BSD License
Classifier: Operating System :: OS Independent
Classifier: Programming Language :: Python
Classifier: Programming Language :: Python :: 3
Classifier: Programming Language :: Python :: 3 :: Only
Classifier: Programming Language :: Python :: 3.10
Classifier: Programming Language :: Python :: 3.11
Classifier: Programming Language :: Python :: 3.12
Classifier: Topic :: Scientific/Engineering
Classifier: Typing :: Typed
Requires-Python: >=3.10
Requires-Dist: equinox>=0.10.6
Requires-Dist: jaxopt>=0.6
Provides-Extra: dev
Requires-Dist: pytest-cov>=3; extra == 'dev'
Requires-Dist: pytest>=6; extra == 'dev'
Provides-Extra: docs
Requires-Dist: autodocsumm~=0.2; extra == 'docs'
Requires-Dist: myst-parser~=0.18; extra == 'docs'
Requires-Dist: sphinx-book-theme~=0.3; extra == 'docs'
Requires-Dist: sphinx-copybutton; extra == 'docs'
Requires-Dist: sphinx-lfs-content~=1.1; extra == 'docs'
Requires-Dist: sphinx~=4.3; extra == 'docs'
Provides-Extra: test
Requires-Dist: pytest-cov>=3; extra == 'test'
Requires-Dist: pytest>=6; extra == 'test'
